CHANGELOG.txt
LICENCE.txt
MANIFEST.in
README.txt
setup.py
colombo/__init__.py
colombo.egg-info/PKG-INFO
colombo.egg-info/SOURCES.txt
colombo.egg-info/dependency_links.txt
colombo.egg-info/top_level.txt