Metadata-Version: 2.1
Name: colombo
Version: 0.0.1
Summary: infomation if Colombo
Home-page: https://github.com/coolsasindu
Author: Sasindu Umesh
Author-email: coolsasindu@gmail.com
License: MIT
Keywords: calculator
Platform: UNKNOWN
Classifier: Development Status :: 5 - Production/Stable
Classifier: Intended Audience :: Education
Classifier: Operating System :: Microsoft :: Windows :: Windows 10
Classifier: License :: OSI Approved :: MIT License
Classifier: Programming Language :: Python :: 3
License-File: LICENCE.txt
